brian2genn/__init__.py
brian2genn/_version.py
brian2genn/binomial.py
brian2genn/codeobject.py
brian2genn/correctness_testing.py
brian2genn/device.py
brian2genn/genn_generator.py
brian2genn/insyn.py
brian2genn/preferences.py
brian2genn/b2glib/convert_synapses.h
brian2genn/sphinxext/__init__.py
brian2genn/sphinxext/briandoc.py
brian2genn/sphinxext/docscrape.py
brian2genn/sphinxext/docscrape_sphinx.py
brian2genn/sphinxext/generate_reference.py
brian2genn/templates/Makefile
brian2genn/templates/engine.cpp
brian2genn/templates/main.cpp
brian2genn/templates/max_row_length_array.cpp
brian2genn/templates/max_row_length_generator.cpp
brian2genn/templates/model.cpp
brian2genn/templates/network.cpp
brian2genn/templates/neuron_code.cpp
brian2genn/templates/project_vcxproj
brian2genn/templates/ratemonitor.cpp
brian2genn/templates/reset.cpp
brian2genn/templates/spikegenerator.cpp
brian2genn/templates/spikemonitor.cpp
brian2genn/templates/statemonitor.cpp
brian2genn/templates/stateupdate.cpp
brian2genn/templates/synapses.cpp
brian2genn/templates/template_notes.txt
brian2genn/templates/threshold.cpp
Brian2GeNN-1.7.0.dist-info/LICENSE
Brian2GeNN-1.7.0.dist-info/METADATA
Brian2GeNN-1.7.0.dist-info/WHEEL
Brian2GeNN-1.7.0.dist-info/top_level.txt
Brian2GeNN-1.7.0.dist-info/RECORD
