Metadata-Version: 2.1
Name: Brian2GeNN
Version: 1.7.0
Summary: An interface to use the GeNN framework as a device in Brian 2
Author: Thomas Nowotny, Marcel Stimberg, Dan Goodman
Project-URL: Documentation, https://brian2genn.readthedocs.io/
Project-URL: Source, https://github.com/brian-team/brian2genn
Project-URL: Tracker, https://github.com/brian-team/brian2genn/issues
Classifier: Development Status :: 4 - Beta
Classifier: Intended Audience :: Science/Research
Classifier: License :: OSI Approved :: GNU General Public License v2 (GPLv2)
Classifier: Natural Language :: English
Classifier: Operating System :: OS Independent
Classifier: Programming Language :: Python
Classifier: Programming Language :: Python :: 3
Classifier: Topic :: Scientific/Engineering :: Bio-Informatics
Requires-Python: >=3.9
License-File: LICENSE
Requires-Dist: brian2 (<2.6,>=2.5.0.2)
Requires-Dist: setuptools (>=61)
Provides-Extra: docs
Requires-Dist: sphinx (>=1.0.1) ; extra == 'docs'
Requires-Dist: sphinxcontrib-issuetracker ; extra == 'docs'
Provides-Extra: test
Requires-Dist: pytest ; extra == 'test'
Requires-Dist: pytest-xdist (>=1.22.3) ; extra == 'test'
